MANIFEST.in
README.rst
setup.py
pybb/__init__.py
pybb/admin.py
pybb/apps.py
pybb/compat.py
pybb/context_processors.py
pybb/defaults.py
pybb/feeds.py
pybb/forms.py
pybb/middleware.py
pybb/models.py
pybb/permissions.py
pybb/profiles.py
pybb/signals.py
pybb/subscription.py
pybb/tests.py
pybb/urls.py
pybb/util.py
pybb/views.py
pybb/locale/de/LC_MESSAGES/django.mo
pybb/locale/de/LC_MESSAGES/django.po
pybb/locale/es/LC_MESSAGES/django.mo
pybb/locale/es/LC_MESSAGES/django.po
pybb/locale/fr/LC_MESSAGES/django.mo
pybb/locale/fr/LC_MESSAGES/django.po
pybb/locale/he/LC_MESSAGES/django.mo
pybb/locale/he/LC_MESSAGES/django.po
pybb/locale/it/LC_MESSAGES/django.mo
pybb/locale/it/LC_MESSAGES/django.po
pybb/locale/ja/LC_MESSAGES/django.mo
pybb/locale/ja/LC_MESSAGES/django.po
pybb/locale/pl/LC_MESSAGES/django.mo
pybb/locale/pl/LC_MESSAGES/django.po
pybb/locale/pt_BR/LC_MESSAGES/django.mo
pybb/locale/pt_BR/LC_MESSAGES/django.po
pybb/locale/ru/LC_MESSAGES/django.mo
pybb/locale/ru/LC_MESSAGES/django.po
pybb/locale/sk/LC_MESSAGES/django.mo
pybb/locale/sk/LC_MESSAGES/django.po
pybb/locale/sv/LC_MESSAGES/django.mo
pybb/locale/sv/LC_MESSAGES/django.po
pybb/locale/uk/LC_MESSAGES/django.mo
pybb/locale/uk/LC_MESSAGES/django.po
pybb/locale/zh/LC_MESSAGES/django.mo
pybb/locale/zh/LC_MESSAGES/django.po
pybb/management/__init__.py
pybb/management/commands/__init__.py
pybb/management/commands/dump_topics.py
pybb/management/commands/migrate_profile.py
pybb/management/commands/pybb_delete_invalid_topics.py
pybb/management/commands/pybb_update_counters.py
pybb/management/commands/supermoderator.py
pybb/markup/__init__.py
pybb/markup/base.py
pybb/markup/bbcode.py
pybb/markup/markdown.py
pybb/migrations/0001_initial.py
pybb/migrations/0002_slugs_optional.py
pybb/migrations/0003_slugs_fill.py
pybb/migrations/0004_slugs_required.py
pybb/migrations/0005_auto_20151108_1528.py
pybb/migrations/0006_forum_subscriptions.py
pybb/migrations/0007_auto_20170111_1504.py
pybb/migrations/__init__.py
pybbm.egg-info/PKG-INFO
pybbm.egg-info/SOURCES.txt
pybbm.egg-info/dependency_links.txt
pybbm.egg-info/not-zip-safe
pybbm.egg-info/requires.txt
pybbm.egg-info/top_level.txt