Metadata-Version: 1.1
Name: pybbm
Version: 0.19.0
Summary: PyBB Modified. Django forum application
Home-page: http://www.pybbm.org/
Author: Pavel Zhukov
Author-email: gelios@gmail.com
License: BSD
Keywords: django application forum board
Platform: UNKNOWN
Classifier: Development Status :: 4 - Beta
Classifier: Environment :: Web Environment
Classifier: Framework :: Django
Classifier: Intended Audience :: Developers
Classifier: License :: OSI Approved :: BSD License
Classifier: Operating System :: OS Independent
Classifier: Programming Language :: Python
Classifier: Programming Language :: Python :: 2
Classifier: Programming Language :: Python :: 2.7
Classifier: Programming Language :: Python :: 3
Classifier: Programming Language :: Python :: 3.4
Classifier: Programming Language :: Python :: 3.5
Classifier: Topic :: Internet :: WWW/HTTP :: Dynamic Content :: Message Boards
Classifier: Topic :: Software Development :: Libraries :: Python Modules
